rbc/__init__.py
rbc/_version.py
rbc/common.thrift
rbc/config.py
rbc/ctools.py
rbc/errors.py
rbc/extension_functions.thrift
rbc/external.py
rbc/irtools.py
rbc/libcudart_ctypes.py
rbc/libfuncs.py
rbc/nrt.py
rbc/omnisci.thrift
rbc/remotejit.py
rbc/remotejit.thrift
rbc/structure_type.py
rbc/targetinfo.py
rbc/typesystem.py
rbc/unicodetype_db.ll
rbc/utils.py
rbc/externals/__init__.py
rbc/externals/cmath.py
rbc/externals/heavydb.py
rbc/externals/libdevice.py
rbc/externals/macros.py
rbc/externals/stdio.py
rbc/heavydb/__init__.py
rbc/heavydb/allocator.py
rbc/heavydb/array.py
rbc/heavydb/buffer.py
rbc/heavydb/column.py
rbc/heavydb/column_array.py
rbc/heavydb/column_flatbuffer.py
rbc/heavydb/column_geolinestring.py
rbc/heavydb/column_geomultilinestring.py
rbc/heavydb/column_geomultipoint.py
rbc/heavydb/column_geomultipolygon.py
rbc/heavydb/column_geopoint.py
rbc/heavydb/column_geopolygon.py
rbc/heavydb/column_list.py
rbc/heavydb/column_list_array.py
rbc/heavydb/column_text_encoding_none.py
rbc/heavydb/day_time_interval.py
rbc/heavydb/flatbuffer_text_encoding_none.py
rbc/heavydb/geo_nested_array.py
rbc/heavydb/geolinestring.py
rbc/heavydb/geomultilinestring.py
rbc/heavydb/geomultipoint.py
rbc/heavydb/geomultipolygon.py
rbc/heavydb/geopoint.py
rbc/heavydb/geopolygon.py
rbc/heavydb/mathimpl.py
rbc/heavydb/metatype.py
rbc/heavydb/npyimpl.py
rbc/heavydb/opaque_pointer.py
rbc/heavydb/pipeline.py
rbc/heavydb/point2d.py
rbc/heavydb/python_operators.py
rbc/heavydb/remoteheavydb.py
rbc/heavydb/row_function_manager.py
rbc/heavydb/string_dict_proxy.py
rbc/heavydb/table_function_manager.py
rbc/heavydb/text_encoding_dict.py
rbc/heavydb/text_encoding_none.py
rbc/heavydb/timestamp.py
rbc/heavydb/utils.py
rbc/heavydb/year_month_time_interval.py
rbc/stdlib/__init__.py
rbc/stdlib/array_api.py
rbc/stdlib/constants.py
rbc/stdlib/creation_functions.py
rbc/stdlib/data_type_functions.py
rbc/stdlib/datatypes.py
rbc/stdlib/elementwise_functions.py
rbc/stdlib/linear_algebra_functions.py
rbc_project-0.13.0.dist-info/LICENSE.txt
rbc_project-0.13.0.dist-info/METADATA
rbc_project-0.13.0.dist-info/WHEEL
rbc_project-0.13.0.dist-info/top_level.txt
rbc_project-0.13.0.dist-info/RECORD
