Metadata-Version: 2.1
Name: rbc-project
Version: 0.13.0
Summary: RBC - Remote Backend Compiler Project
Home-page: https://github.com/xnd-project/rbc
Author: Pearu Peterson
Author-email: pearu.peterson@quansight.com
Maintainer: Pearu Peterson
License: BSD
Platform: Cross Platform
Classifier: Intended Audience :: Developers
Classifier: License :: OSI Approved :: BSD License
Classifier: Programming Language :: Python :: 3
Classifier: Programming Language :: Python :: 3.7
Classifier: Programming Language :: Python :: 3.8
Classifier: Programming Language :: Python :: 3.9
Classifier: Programming Language :: Python :: 3.10
Classifier: Operating System :: OS Independent
Classifier: Topic :: Software Development
License-File: LICENSE.txt
Requires-Dist: numba >=0.55
Requires-Dist: llvmlite
Requires-Dist: tblib
Requires-Dist: thriftpy2
Requires-Dist: netifaces
Requires-Dist: packaging
